demo/__init__.py
demo/sample.py
demo/test/__init__.py
demo/test/test_demo.py
PythonTemplateDemo-0.0.0.dist-info/DESCRIPTION.rst
PythonTemplateDemo-0.0.0.dist-info/entry_points.txt
PythonTemplateDemo-0.0.0.dist-info/METADATA
PythonTemplateDemo-0.0.0.dist-info/metadata.json
PythonTemplateDemo-0.0.0.dist-info/RECORD
PythonTemplateDemo-0.0.0.dist-info/top_level.txt
PythonTemplateDemo-0.0.0.dist-info/WHEEL
