Metadata-Version: 2.0
Name: PythonTemplateDemo
Version: 0.0.0
Summary: PythonTemplateDemo is a Python 3 package template.
Home-page: https://github.com/jacebrowning/template-python-demo
Author: Jace Browning
Author-email: jacebrowning@gmail.com
License: WTFPL
Platform: UNKNOWN
Classifier: Development Status :: 1 - Planning
Classifier: Natural Language :: English
Classifier: Operating System :: OS Independent
Classifier: Programming Language :: Python :: 3.3
Requires-Dist: testpackage (==2.26)
Requires-Dist: newrelic-plugin-agent (==1.3.0)
